[{"nombre":"AAS"},{"nombre":"ADELAN"},{"nombre":"ADRENALINA"},{"nombre":"AILYN"},{"nombre":"ALBIS"},{"nombre":"ALDARA"},{"nombre":"ALMAX"},{"nombre":"ALPRAZOLAM"},{"nombre":"AMOXICILINA"},{"nombre":"ANTIN"},{"nombre":"APIRETAL"},{"nombre":"ASPIRINA "},{"nombre":"ATORVASTATINA"},{"nombre":"ATRACURIO"},{"nombre":"AZALIA"},{"nombre":"AZITROMICINA"},{"nombre":"BCG"},{"nombre":"BETAMETASONA"},{"nombre":"BIOTINA"},{"nombre":"BOREA"},{"nombre":"BUDESONIDA"},{"nombre":"BUDESONIDA"},{"nombre":"BUSCAPINA"},{"nombre":"CAFINITRINA"},{"nombre":"CANNABIDIOL"},{"nombre":"CARENA"},{"nombre":"CEFTRIAXONA"},{"nombre":"CERISE"},{"nombre":"CETIRIZINA"},{"nombre":"CITALOPRAM"},{"nombre":"CITRATO"},{"nombre":"CLEXANE"},{"nombre":"CLONAZEPAM"},{"nombre":"CLORFENAMINA"},{"nombre":"CODEINA FOSFATO"},{"nombre":"COLCHICINA"},{"nombre":"CORTISON"},{"nombre":"CYTOTEC"},{"nombre":"DALSY"},{"nombre":"DEXAMETASONA"},{"nombre":"DIANE"},{"nombre":"DIAZEPAM"},{"nombre":"DICLOFENACO"},{"nombre":"EFEDRINA "},{"nombre":"EMEND "},{"nombre":"EMLA "},{"nombre":"ENALAPRIL"},{"nombre":"ENANTYUM"},{"nombre":"ENEAS "},{"nombre":"ENIT "},{"nombre":"ENOXAPARINA"},{"nombre":"EPINEFRINA"},{"nombre":"ESCITALOPRAM"},{"nombre":"ESTRADIOL"},{"nombre":"EVISTA "},{"nombre":"FENTANILO"},{"nombre":"FLUOXETINA"},{"nombre":"FLUTOX"},{"nombre":"FOLICO"},{"nombre":"FRENADOL"},{"nombre":"GALDAR"},{"nombre":"GALIO"},{"nombre":"GELOCATIL "},{"nombre":"GINKGO"},{"nombre":"GLUCOSA "},{"nombre":"HEMOAL"},{"nombre":"HEPARINA "},{"nombre":"HIDROCORTISONA"},{"nombre":"HIDROXICLOROQUINA"},{"nombre":"HIERRO"},{"nombre":"IBUPROFENO"},{"nombre":"IDEOS "},{"nombre":"IODO"},{"nombre":"ISOTRETINOINA"},{"nombre":"IVERMECTINA"},{"nombre":"KETOROLACO"},{"nombre":"KONEX "},{"nombre":"LEXATIN "},{"nombre":"LIDOCAINA"},{"nombre":"LORATADINA"},{"nombre":"LORAZEPAM"},{"nombre":"LOSARTAN "},{"nombre":"METAMIZOL"},{"nombre":"METASEDIN"},{"nombre":"METFORMINA"},{"nombre":"METOTREXATO"},{"nombre":"MIDAZOLAM"},{"nombre":"MINOXIDIL"},{"nombre":"MIRENA"},{"nombre":"MISOPROSTOL"},{"nombre":"MITEN "},{"nombre":"MORFINA"},{"nombre":"NABILA "},{"nombre":"NAPROXENO"},{"nombre":"NEXIUM"},{"nombre":"NITROGLICERINA"},{"nombre":"NOLOTIL "},{"nombre":"OMEPRAZOL"},{"nombre":"ORFIDAL "},{"nombre":"OSPOR "},{"nombre":"OXITOCINA"},{"nombre":"PANADOL"},{"nombre":"PARACETAMOL"},{"nombre":"PAROXETINA"},{"nombre":"PASIFLORA"},{"nombre":"PNEUMO "},{"nombre":"PREDNISONA"},{"nombre":"PREGABALINA"},{"nombre":"PROGESTERONA"},{"nombre":"PROPOFOL"},{"nombre":"PROZAC"},{"nombre":"QUETIAPINA"},{"nombre":"RANITIDINA"},{"nombre":"REMDESIVIR"},{"nombre":"RICINO"},{"nombre":"RIVOTRIL "},{"nombre":"ROSUVASTATINA"},{"nombre":"SALBUTAMOL"},{"nombre":"SERTRALINA"},{"nombre":"TELO"},{"nombre":"TOCILIZUMAB"},{"nombre":"TORADOL "},{"nombre":"TRAMADOL"},{"nombre":"VALIUM "},{"nombre":"VAPORUB"},{"nombre":"VENTOLIN"},{"nombre":"VIAGRA "},{"nombre":"XICIL "},{"nombre":"YASMIN"},{"nombre":"ZINC"},{"nombre":"ZOLPIDEM"}]